<?xml version="1.0" encoding="utf-8"?>
<SoundBanksInfo Platform="Windows" BasePlatform="Windows" SchemaVersion="11" SoundbankVersion="132">
	<RootPaths>
		<ProjectRoot>C:\Schule\SJ1819\Jahresprojekt\MinoWwise\MinoWwise\</ProjectRoot>
		<SourceFilesRoot>C:\Schule\SJ1819\Jahresprojekt\MinoWwise\MinoWwise\.cache\Windows\</SourceFilesRoot>
		<SoundBanksRoot>C:\Schule\SJ1819\Jahresprojekt\MinoWwise\MinoWwise\GeneratedSoundBanks\Windows\</SoundBanksRoot>
		<ExternalSourcesInputFile></ExternalSourcesInputFile>
		<ExternalSourcesOutputRoot>C:\Schule\SJ1819\Jahresprojekt\MinoWwise\MinoWwise\GeneratedSoundBanks\Windows</ExternalSourcesOutputRoot>
	</RootPaths>
	<DialogueEvents/>
	<StreamedFiles/>
	<MediaFilesNotInAnyBank/>
	<SoundBanks>
		<SoundBank Id="1355168291" Language="SFX">
			<ObjectPath>Init</ObjectPath>
			<ShortName>Init</ShortName>
			<Path>Init.bnk</Path>
		</SoundBank>
		<SoundBank Id="1949491649" Language="SFX">
			<ObjectPath>\SoundBanks\Default Work Unit\MinoSoundbankNew</ObjectPath>
			<ShortName>MinoSoundbankNew</ShortName>
			<Path>MinoSoundbankNew.bnk</Path>
			<IncludedEvents>
				<Event Id="3562358968" Name="Play_Hagi_footsteps_grass" ObjectPath="\Events\Default Work Unit\Play_Hagi_footsteps_grass" MaxAttenuation="60.000000"/>
				<Event Id="3200425469" Name="Play_Player_Footsteps_walk_stone" ObjectPath="\Events\Default Work Unit\Play_Player_Footsteps_walk_stone"/>
			</IncludedEvents>
			<IncludedMemoryFiles>
				<File Id="414668148" Language="SFX">
					<ShortName>Hagibaer_stampfen.wav</ShortName>
					<Path>SFX\Hagibaer_stampfen_56D34C19.wem</Path>
				</File>
			</IncludedMemoryFiles>
		</SoundBank>
	</SoundBanks>
</SoundBanksInfo>
